[
  {
    "method": "OursSmc(num_steps=100, num_particles=1000, temperature=1000.0, max_arity=2)",
    "domain": "physics",
    "file": "scientific_unsolved_4h_ellisk_2019-07-20T18.05.46__bench000_it0",
    "initial_cost": 567,
    "final_cost": 376,
    "compression_ratio": 1.5079787234042554,
    "elapsed_secs": 1.233402369,
    "library": [
      "fn_0: (lam (lam (?#0 $1 $0)))",
      "fn_1: (lam (map (lam (*. $0 ?#0)) $0))",
      "fn_2: (lam (lam (?#0 $0 (*. $1 $1))))",
      "fn_3: (+. 1. 1.)",
      "fn_4: (fold ?#0 0. (?#1 +.))",
      "fn_5: (lam (lam (*. $0 (/. (*. $1 $0) fn_3))))",
      "fn_6: (lam (lam (lam (+. $2 (*. $0 $1)))))",
      "fn_7: (/. 1.)",
      "fn_8: (lam (lam (*. $1 (/. $1 $0))))",
      "fn_9: (lam (lam (fn_4 (zip $0 $1 (fn_0 *.)) fn_0)))",
      "fn_10: (fn_0 /.)",
      "fn_11: (lam (fn_7 $0))",
      "fn_12: (lam (fn_4 $0 fn_0))",
      "fn_13: (lam (*. $0 (*. $0 ?#0)))",
      "fn_14: (fn_0 *.)",
      "fn_15: (+. ?#0 ?#0)"
    ],
    "egraph_min_term_size": 568.0
  },
  {
    "method": "OursSmc(num_steps=100, num_particles=1000, temperature=1000.0, max_arity=2)",
    "domain": "physics",
    "file": "scientific_unsolved_4h_ellisk_2019-07-20T18.05.46__bench001_it1",
    "initial_cost": 474,
    "final_cost": 355,
    "compression_ratio": 1.3352112676056338,
    "elapsed_secs": 1.064743785,
    "library": [
      "fn_0: (lam (lam (lam (lam (+. (*. (+. (fn_137 $0 $1) $2) $0) $3)))))",
      "fn_1: (lam (lam (?#0 $0 $1)))",
      "fn_2: (lam (lam (fn_141 $1 $0)))",
      "fn_3: (lam (lam (/. $1 $0)))",
      "fn_4: (lam (lam (lam (+. $2 (*. $0 $1)))))",
      "fn_5: (lam (lam (*. $1 (/. $1 $0))))",
      "fn_6: (lam (fn_140 $0))",
      "fn_7: (*. ?#0 ?#0)",
      "fn_8: (lam (lam (fn_138 $0 (fn_140 $1))))",
      "fn_9: (lam (lam (*. $0 (?#0 $0 $1))))",
      "fn_10: (lam (fn_139 $0))",
      "fn_11: (fn_1 *.)",
      "fn_12: (fn_1 fn_136)"
    ],
    "egraph_min_term_size": 475.0
  },
  {
    "method": "OursSmc(num_steps=100, num_particles=1000, temperature=1000.0, max_arity=2)",
    "domain": "physics",
    "file": "scientific_unsolved_4h_ellisk_2019-07-20T18.05.46__bench002_it2",
    "initial_cost": 438,
    "final_cost": 327,
    "compression_ratio": 1.3394495412844036,
    "elapsed_secs": 0.93986309,
    "library": [
      "fn_0: (lam (lam (?#0 $0 $1)))",
      "fn_1: (lam (lam (/. $1 $0)))",
      "fn_2: (lam (lam (fn_141 $1 $0)))",
      "fn_3: (lam (lam (lam (+. (*. $1 $0) $2))))",
      "fn_4: (lam (lam (lam (lam (fn_144 $3 $2 $1 $0)))))",
      "fn_5: (lam (lam (fn_142 $1 $1 $0 empty)))",
      "fn_6: (lam (fn_140 $0))",
      "fn_7: (lam (lam (fn_138 $0 (fn_140 $1))))",
      "fn_8: (lam (*. (*. ?#0 $0) $0))",
      "fn_9: (fn_138 1. 1.)",
      "fn_10: (lam (fn_139 $0))",
      "fn_11: (fn_0 *.)",
      "fn_12: (fn_0 fn_136)"
    ],
    "egraph_min_term_size": 439.0
  },
  {
    "method": "OursSmc(num_steps=100, num_particles=1000, temperature=1000.0, max_arity=2)",
    "domain": "physics",
    "file": "scientific_unsolved_4h_ellisk_2019-07-20T18.05.46__bench003_it3",
    "initial_cost": 527,
    "final_cost": 402,
    "compression_ratio": 1.3109452736318408,
    "elapsed_secs": 1.223962491,
    "library": [
      "fn_0: (lam (lam (?#0 $0 $1)))",
      "fn_1: (lam (lam (*. (+. pi pi) (fn_145 (/. $1 $0)))))",
      "fn_2: (lam (lam (fn_141 $1 $0)))",
      "fn_3: (lam (lam (lam (+. $2 (*. $1 $0)))))",
      "fn_4: (lam (lam (/. $1 $0)))",
      "fn_5: (lam (lam (lam (lam (fn_144 $3 $2 $1 $0)))))",
      "fn_6: (lam (fn_140 $0))",
      "fn_7: (lam (lam (fn_142 $1 $1 $0 empty)))",
      "fn_8: (lam (lam (fn_138 $0 (fn_140 $1))))",
      "fn_9: (lam (*. $0 (*. $0 ?#0)))",
      "fn_10: (lam (fn_139 $0))",
      "fn_11: (lam (?#0 (fn_136 $0 $0)))",
      "fn_12: (fn_0 *.)",
      "fn_13: (fn_0 fn_136)"
    ],
    "egraph_min_term_size": 528.0
  },
  {
    "method": "OursSmc(num_steps=100, num_particles=1000, temperature=1000.0, max_arity=2)",
    "domain": "physics",
    "file": "scientific_unsolved_4h_ellisk_2019-07-20T18.05.46__bench004_it4",
    "initial_cost": 521,
    "final_cost": 418,
    "compression_ratio": 1.2464114832535884,
    "elapsed_secs": 1.1991860970000001,
    "library": [
      "fn_0: (lam (lam (?#0 $0 $1 $1 $0)))",
      "fn_1: (fn_0 (lam (lam fn_141)))",
      "fn_2: (fn_0 (lam (lam /.)))",
      "fn_3: (lam (lam (lam (+. (*. $1 $0) $2))))",
      "fn_4: (lam (lam (?#0 $0 $1)))",
      "fn_5: (lam (fn_140 $0))",
      "fn_6: (lam (lam (fn_142 $1 $1 $0 empty)))",
      "fn_7: (lam (lam (fn_138 $0 (fn_140 $1))))",
      "fn_8: (lam (*. $0 (*. ?#0 $0)))",
      "fn_9: (fn_0 (lam (lam *.)))",
      "fn_10: (fn_0 (lam (lam fn_147)))",
      "fn_11: (lam (fn_139 $0))",
      "fn_12: (lam (?#0 (fn_136 $0 $0)))",
      "fn_13: (fn_4 fn_136)"
    ],
    "egraph_min_term_size": 522.0
  },
  {
    "method": "OursSmc(num_steps=100, num_particles=1000, temperature=1000.0, max_arity=2)",
    "domain": "physics",
    "file": "scientific_unsolved_4h_ellisk_2019-07-20T18.09.34__bench000_it0",
    "initial_cost": 600,
    "final_cost": 378,
    "compression_ratio": 1.5873015873015872,
    "elapsed_secs": 1.432049534,
    "library": [
      "fn_0: (lam (lam (?#0 $1 $0)))",
      "fn_1: (fold ?#0 0. (lam (lam (+. $0 (*. $1 $1)))))",
      "fn_2: (map (lam (*. $0 ?#0)))",
      "fn_3: (+. 1. 1.)",
      "fn_4: (fold ?#0 0. (fn_0 +.))",
      "fn_5: (lam (lam (/. (*. $0 $0) (/. fn_3 $1))))",
      "fn_6: (lam (lam (fn_4 (zip $0 $1 (fn_0 *.)))))",
      "fn_7: (lam (lam (lam (+. $2 (*. $1 $0)))))",
      "fn_8: (/. 1.)",
      "fn_9: (lam (lam (lam (/. (*. $1 $2) (fn_1 $0)))))",
      "fn_10: (lam (lam (*. $1 (/. $1 $0))))",
      "fn_11: (lam (lam (zip $0 $1 (fn_0 +.))))",
      "fn_12: (lam (lam (fn_2 ?#0 $0)))",
      "fn_13: (fn_0 /.)",
      "fn_14: (lam (fn_8 $0))",
      "fn_15: (lam (*. $0 (*. $0 ?#0)))",
      "fn_16: (lam (fn_4 $0))",
      "fn_17: (fn_0 *.)",
      "fn_18: (*. ?#0 ?#0)",
      "fn_19: (/. ?#0 fn_3)"
    ],
    "egraph_min_term_size": 601.0
  },
  {
    "method": "OursSmc(num_steps=100, num_particles=1000, temperature=1000.0, max_arity=2)",
    "domain": "physics",
    "file": "scientific_unsolved_4h_ellisk_2019-07-20T18.09.34__bench001_it1",
    "initial_cost": 490,
    "final_cost": 339,
    "compression_ratio": 1.4454277286135693,
    "elapsed_secs": 1.156960773,
    "library": [
      "fn_0: (lam (lam (?#0 $1 $0)))",
      "fn_1: (fold (cdr ?#0) (car ?#0) (lam (lam (fn_148 $0 $1))))",
      "fn_2: (lam (lam (lam (+. (+. (*. $0 (fn_150 $0 $1)) ?#0) (*. $2 $0)))))",
      "fn_3: (lam (lam (?#0 $0 $1)))",
      "fn_4: (lam (lam (lam (+. $2 (*. $1 $0)))))",
      "fn_5: (lam (lam (*. (/. $1 $0) $1)))",
      "fn_6: (lam (fn_140 $0))",
      "fn_7: (lam (lam (lam (fn_154 $1 $2 $0))))",
      "fn_8: (lam (lam (fn_152 $0 (fn_140 $1))))",
      "fn_9: (fn_0 /.)",
      "fn_10: (fn_0 fn_153)",
      "fn_11: (lam (*. $0 (*. $0 ?#0)))",
      "fn_12: (lam (fn_139 $0))",
      "fn_13: (lam (fn_1 $0))",
      "fn_14: (fn_3 fn_136)",
      "fn_15: (fn_0 *.)"
    ],
    "egraph_min_term_size": 491.0
  },
  {
    "method": "OursSmc(num_steps=100, num_particles=1000, temperature=1000.0, max_arity=2)",
    "domain": "physics",
    "file": "scientific_unsolved_4h_ellisk_2019-07-20T18.09.34__bench002_it2",
    "initial_cost": 449,
    "final_cost": 332,
    "compression_ratio": 1.3524096385542168,
    "elapsed_secs": 1.179072489,
    "library": [
      "fn_0: (lam (lam (?#0 $1 $0)))",
      "fn_1: (lam (lam (lam (+. (*. $1 $0) $2))))",
      "fn_2: (lam (lam (?#0 $0 $1)))",
      "fn_3: (lam (lam (*. $1 (/. $1 $0))))",
      "fn_4: (lam (fn_140 $0))",
      "fn_5: (lam (lam (lam (fn_154 $1 $2 $0))))",
      "fn_6: (lam (lam (fn_152 $0 (fn_140 $1))))",
      "fn_7: (fn_0 /.)",
      "fn_8: (fn_0 fn_153)",
      "fn_9: (lam (*. (*. ?#0 $0) $0))",
      "fn_10: (lam (fn_139 $0))",
      "fn_11: (lam (fn_155 $0))",
      "fn_12: (fn_0 *.)",
      "fn_13: (fn_2 fn_136)",
      "fn_14: (*. ?#0 ?#0)"
    ],
    "egraph_min_term_size": 450.0
  },
  {
    "method": "OursSmc(num_steps=100, num_particles=1000, temperature=1000.0, max_arity=2)",
    "domain": "physics",
    "file": "scientific_unsolved_4h_ellisk_2019-07-20T18.09.34__bench003_it3",
    "initial_cost": 433,
    "final_cost": 310,
    "compression_ratio": 1.396774193548387,
    "elapsed_secs": 1.034068777,
    "library": [
      "fn_0: (lam (lam (?#0 $1 $0)))",
      "fn_1: (lam (lam (?#0 $0 $1)))",
      "fn_2: (lam (lam (lam (+. $2 (*. $0 $1)))))",
      "fn_3: (lam (lam (*. $1 (/. $1 $0))))",
      "fn_4: (lam (fn_140 $0))",
      "fn_5: (lam (lam (lam (fn_154 $1 $2 $0))))",
      "fn_6: (lam (lam (fn_152 $0 (fn_140 $1))))",
      "fn_7: (fn_0 fn_153)",
      "fn_8: (fn_0 /.)",
      "fn_9: (lam (*. $0 (*. $0 ?#0)))",
      "fn_10: (fn_150 1. 1.)",
      "fn_11: (lam (fn_139 $0))",
      "fn_12: (lam (fn_155 $0))",
      "fn_13: (fn_1 fn_136)",
      "fn_14: (fn_0 *.)"
    ],
    "egraph_min_term_size": 434.0
  },
  {
    "method": "OursSmc(num_steps=100, num_particles=1000, temperature=1000.0, max_arity=2)",
    "domain": "physics",
    "file": "scientific_unsolved_4h_ellisk_2019-07-20T18.09.34__bench004_it4",
    "initial_cost": 507,
    "final_cost": 356,
    "compression_ratio": 1.4241573033707866,
    "elapsed_secs": 1.14493717,
    "library": [
      "fn_0: (lam (lam (?#0 $1 $0)))",
      "fn_1: (lam (lam (lam (fn_153 (fn_154 $1 (fn_157 (fn_154 $2 $2 $0)) $0) $0))))",
      "fn_2: (lam (lam (lam (+. $2 (*. $1 $0)))))",
      "fn_3: (lam (lam (?#0 $0 $1)))",
      "fn_4: (lam (lam (fn_151 (fn_157 (/. $0 $1)) pi)))",
      "fn_5: (lam (lam (*. $1 (/. $1 $0))))",
      "fn_6: (lam (fn_140 $0))",
      "fn_7: (lam (lam (lam (fn_154 $1 $2 $0))))",
      "fn_8: (lam (lam (fn_152 $0 (fn_140 $1))))",
      "fn_9: (fn_0 fn_153)",
      "fn_10: (fn_0 /.)",
      "fn_11: (lam (*. $0 (*. $0 ?#0)))",
      "fn_12: (lam (fn_139 $0))",
      "fn_13: (lam (fn_155 $0))",
      "fn_14: (fn_3 fn_136)",
      "fn_15: (fn_0 *.)"
    ],
    "egraph_min_term_size": 508.0
  },
  {
    "method": "OursSmc(num_steps=100, num_particles=1000, temperature=1000.0, max_arity=2)",
    "domain": "physics",
    "file": "scientific_unsolved_4h_ellisk_2019-07-20T18.09.34__bench005_it5",
    "initial_cost": 518,
    "final_cost": 369,
    "compression_ratio": 1.4037940379403795,
    "elapsed_secs": 1.2491942,
    "library": [
      "fn_0: (lam (lam (?#0 $1 $0)))",
      "fn_1: (lam (lam (lam (?#0 $1 $2 $0))))",
      "fn_2: (lam (lam (?#0 $0 $1)))",
      "fn_3: (lam (lam (lam (+. $2 (*. $1 $0)))))",
      "fn_4: (lam (lam (*. $1 (/. $1 $0))))",
      "fn_5: (lam (fn_140 $0))",
      "fn_6: (fn_0 fn_153)",
      "fn_7: (lam (lam (fn_152 $0 (fn_140 $1))))",
      "fn_8: (fn_0 /.)",
      "fn_9: (lam (*. (*. $0 ?#0) $0))",
      "fn_10: (lam (fn_155 $0))",
      "fn_11: (lam (fn_139 $0))",
      "fn_12: (fn_1 fn_159)",
      "fn_13: (fn_2 fn_136)",
      "fn_14: (fn_0 fn_158)",
      "fn_15: (fn_0 *.)",
      "fn_16: (fn_1 fn_154)"
    ],
    "egraph_min_term_size": 519.0
  },
  {
    "method": "OursSmc(num_steps=100, num_particles=1000, temperature=1000.0, max_arity=2)",
    "domain": "physics",
    "file": "scientific_unsolved_4h_ellisk_2019-07-20T18.09.34__bench006_it7",
    "initial_cost": 527,
    "final_cost": 386,
    "compression_ratio": 1.3652849740932642,
    "elapsed_secs": 1.410266945,
    "library": [
      "fn_0: (lam (lam (?#0 $1 $0)))",
      "fn_1: (lam (lam (?#0 $0 $1)))",
      "fn_2: (lam (fn_140 $0))",
      "fn_3: (lam (lam (lam (?#0 $1 $2 $0))))",
      "fn_4: (lam (lam (lam (+. $2 (*. $0 $1)))))",
      "fn_5: (lam (lam (fn_152 $0 (fn_140 $1))))",
      "fn_6: (fn_0 fn_153)",
      "fn_7: (lam (lam (*. $1 (/. $1 $0))))",
      "fn_8: (fn_0 /.)",
      "fn_9: (lam (*. $0 (*. $0 ?#0)))",
      "fn_10: (lam (fn_139 $0))",
      "fn_11: (lam (fn_155 $0))",
      "fn_12: (fn_1 fn_136)",
      "fn_13: (fn_0 fn_158)",
      "fn_14: (fn_3 fn_154)",
      "fn_15: (fn_0 *.)",
      "fn_16: (fn_3 fn_159)"
    ],
    "egraph_min_term_size": 528.0
  },
  {
    "method": "OursSmc(num_steps=100, num_particles=1000, temperature=1000.0, max_arity=2)",
    "domain": "physics",
    "file": "scientific_unsolved_4h_ellisk_2019-07-20T18.13.12__bench000_it0",
    "initial_cost": 567,
    "final_cost": 361,
    "compression_ratio": 1.5706371191135735,
    "elapsed_secs": 1.316134204,
    "library": [
      "fn_0: (lam (lam (map (lam (*. $2 $0)) $0)))",
      "fn_1: (fold ?#0 0. (lam (lam (+. (?#1 $0 $1) $0))))",
      "fn_2: (lam (lam (?#0 $1 $0)))",
      "fn_3: (lam (lam (*. $0 (/. (*. $1 $0) (+. 1. 1.)))))",
      "fn_4: (lam (lam (lam (/. $2 (/. (fn_1 $0 (lam (lam (*. $1 $1)))) $1)))))",
      "fn_5: (lam (lam (fn_1 (zip $0 $1 (fn_2 *.)) (lam (lam $1)))))",
      "fn_6: (lam (lam (lam (+. $2 (*. $0 $1)))))",
      "fn_7: (/. 1.)",
      "fn_8: (lam (lam (*. $1 (/. $1 $0))))",
      "fn_9: (+. ?#0 ?#0)",
      "fn_10: (lam (fn_1 $0 (lam (lam $1))))",
      "fn_11: (fn_2 /.)",
      "fn_12: (lam (fn_7 $0))",
      "fn_13: (lam (*. (*. $0 ?#0) $0))",
      "fn_14: (fn_9 1.)",
      "fn_15: (*. ?#0 ?#0)",
      "fn_16: (fn_2 *.)"
    ],
    "egraph_min_term_size": 568.0
  },
  {
    "method": "OursSmc(num_steps=100, num_particles=1000, temperature=1000.0, max_arity=2)",
    "domain": "physics",
    "file": "scientific_unsolved_4h_ellisk_2019-07-20T18.13.12__bench001_it1",
    "initial_cost": 505,
    "final_cost": 365,
    "compression_ratio": 1.3835616438356164,
    "elapsed_secs": 1.340243798,
    "library": [
      "fn_0: (lam (lam (fn_153 $1 $0)))",
      "fn_1: (lam (lam (/. $1 $0)))",
      "fn_2: (lam (lam (?#0 $0 $1)))",
      "fn_3: (lam (lam (lam (lam (+. (*. (+. $2 (fn_137 $0 $1)) $0) $3)))))",
      "fn_4: (lam (lam (?#0 $1 (/. $1 $0))))",
      "fn_5: (*. ?#0 ?#0)",
      "fn_6: (lam (fn_140 $0))",
      "fn_7: (lam (lam (lam (+. $2 (*. $1 $0)))))",
      "fn_8: (lam (lam (fn_137 (fn_5 $0) $1)))",
      "fn_9: (lam (lam (lam (fn_161 $0 (*. $2 $1)))))",
      "fn_10: (lam (lam (*. $0 (?#0 $0 $1))))",
      "fn_11: (lam (fn_139 $0))",
      "fn_12: (fn_2 *.)",
      "fn_13: (fn_4 *.)",
      "fn_14: (fn_2 fn_136)",
      "fn_15: (+. (fn_5 ?#0))",
      "fn_16: (+. ?#0 ?#0)"
    ],
    "egraph_min_term_size": 506.0
  },
  {
    "method": "OursSmc(num_steps=100, num_particles=1000, temperature=1000.0, max_arity=2)",
    "domain": "physics",
    "file": "scientific_unsolved_4h_ellisk_2019-07-20T18.16.45__bench000_it0",
    "initial_cost": 567,
    "final_cost": 356,
    "compression_ratio": 1.5926966292134832,
    "elapsed_secs": 1.3481309719999999,
    "library": [
      "fn_0: (lam (lam (?#0 $1 $0)))",
      "fn_1: (lam (lam (map (lam (*. $2 $0)) $0)))",
      "fn_2: (fold ?#0 0. (lam (lam (+. $0 (*. $1 $1)))))",
      "fn_3: (/. ?#0 (+. 1. 1.))",
      "fn_4: (fold ?#0 0. (fn_0 +.))",
      "fn_5: (lam (lam (*. $0 (fn_3 (*. $0 $1)))))",
      "fn_6: (/. 1.)",
      "fn_7: (lam (lam (fn_4 (zip $0 $1 (fn_0 *.)))))",
      "fn_8: (lam (lam (lam (+. (*. $0 $1) $2))))",
      "fn_9: (lam (lam (*. (/. $1 $0) $1)))",
      "fn_10: (fn_0 /.)",
      "fn_11: (lam (fn_6 $0))",
      "fn_12: (lam (*. $0 (*. $0 ?#0)))",
      "fn_13: (lam (fn_4 $0))",
      "fn_14: (fn_0 *.)",
      "fn_15: (+. ?#0 ?#0)",
      "fn_16: (*. ?#0 ?#0)",
      "fn_17: (lam (lam (*. $0 (?#0 $0 $1))))"
    ],
    "egraph_min_term_size": 568.0
  },
  {
    "method": "OursSmc(num_steps=100, num_particles=1000, temperature=1000.0, max_arity=2)",
    "domain": "physics",
    "file": "scientific_unsolved_4h_ellisk_2019-07-20T18.16.45__bench001_it1",
    "initial_cost": 576,
    "final_cost": 402,
    "compression_ratio": 1.4328358208955223,
    "elapsed_secs": 1.301823551,
    "library": [
      "fn_0: (lam (lam (?#0 $1 $0)))",
      "fn_1: (power ?#0 (fn_163 1.))",
      "fn_2: (lam (lam (lam (lam (+. $3 (*. $0 (+. $2 (fn_163 (*. $1 $0)))))))))",
      "fn_3: (lam (lam (fn_141 (fn_164 $1 (/. ?#0 (fn_1 (fn_162 $0))) $0) $0)))",
      "fn_4: (lam (lam (fn_151 (fn_1 (/. $0 $1)) pi)))",
      "fn_5: (lam (lam (*. (fn_163 (*. $1 $0)) $0)))",
      "fn_6: (lam (lam (lam (+. (*. $1 $0) $2))))",
      "fn_7: (lam (lam (*. $1 (/. $1 $0))))",
      "fn_8: (lam (fn_140 $0))",
      "fn_9: (lam (lam (lam (fn_164 $1 $2 $0))))",
      "fn_10: (fn_0 /.)",
      "fn_11: (fn_0 fn_141)",
      "fn_12: (lam (lam (fn_136 $0 $1)))",
      "fn_13: (lam (*. $0 (*. $0 ?#0)))",
      "fn_14: (lam (fn_139 $0))",
      "fn_15: (fn_0 *.)",
      "fn_16: (fn_162 (cons ?#0 (cons ?#1 empty)))"
    ],
    "egraph_min_term_size": 577.0
  },
  {
    "method": "OursSmc(num_steps=100, num_particles=1000, temperature=1000.0, max_arity=2)",
    "domain": "physics",
    "file": "scientific_unsolved_4h_ellisk_2019-07-20T18.20.13__bench000_it0",
    "initial_cost": 658,
    "final_cost": 422,
    "compression_ratio": 1.5592417061611374,
    "elapsed_secs": 1.510567835,
    "library": [
      "fn_0: (lam (lam (+. $1 $0)))",
      "fn_1: (lam (*. $0 (?#0 $0)))",
      "fn_2: (fold ?#0 0. (lam (lam (+. $0 (*. $1 $1)))))",
      "fn_3: (lam (fold $0 (map (fn_1 (lam 0.)) (car $0)) (lam (lam (zip $0 $1 fn_0)))))",
      "fn_4: (/. ?#0 (+. 1. 1.))",
      "fn_5: (lam (/. ?#0 $0))",
      "fn_6: (lam (lam (map (fn_1 (lam ?#0)) $0)))",
      "fn_7: (lam (fold (zip $0 ?#0 (lam (fn_1 (lam $2)))) 0. fn_0))",
      "fn_8: (lam (lam (*. $1 (/. $1 $0))))",
      "fn_9: (lam (lam (lam (/. (*. $2 $1) (fn_2 $0)))))",
      "fn_10: (lam (lam (lam (+. $2 (*. $1 $0)))))",
      "fn_11: (lam (fold $0 0. fn_0))",
      "fn_12: (lam (fn_1 (lam (fn_4 (*. ?#0 $0)))))",
      "fn_13: (/. 1.)",
      "fn_14: (fn_5 1.)",
      "fn_15: (*. ?#0 ?#0)",
      "fn_16: (+. ?#0 ?#0)",
      "fn_17: (lam (fn_1 ?#0))"
    ],
    "egraph_min_term_size": 659.0
  },
  {
    "method": "OursSmc(num_steps=100, num_particles=1000, temperature=1000.0, max_arity=2)",
    "domain": "physics",
    "file": "scientific_unsolved_4h_ellisk_2019-07-20T18.20.13__bench001_it1",
    "initial_cost": 463,
    "final_cost": 339,
    "compression_ratio": 1.3657817109144543,
    "elapsed_secs": 1.087236868,
    "library": [
      "fn_0: (lam (lam (lam (lam (+. (*. (+. (fn_150 $0 $1) $2) $0) $3)))))",
      "fn_1: (lam (lam (?#0 $1 $0)))",
      "fn_2: (lam (lam (lam (+. $2 (*. $1 $0)))))",
      "fn_3: (lam (lam (*. $1 (/. $1 $0))))",
      "fn_4: (lam (fn_140 $0))",
      "fn_5: (lam (lam (lam (fn_168 $1 $2 $0))))",
      "fn_6: (lam (lam (fn_167 $0 (fn_140 $1))))",
      "fn_7: (fn_1 fn_141)",
      "fn_8: (fn_1 /.)",
      "fn_9: (lam (lam (?#0 $0 $1)))",
      "fn_10: (lam (*. (*. ?#0 $0) $0))",
      "fn_11: (lam (fn_165 $0))",
      "fn_12: (lam (fn_139 $0))",
      "fn_13: (fn_1 *.)",
      "fn_14: (fn_9 fn_136)",
      "fn_15: (*. ?#0 ?#0)"
    ],
    "egraph_min_term_size": 464.0
  }
]