[
  {
    "method": "OursBf(num_steps=500, max_arity=2)",
    "domain": "logo",
    "file": "logo_batch_50_1h_ellisk_2019-03-23T14.02.03__bench000_it0",
    "initial_cost": 737,
    "final_cost": 653,
    "compression_ratio": 1.1286370597243491,
    "elapsed_secs": 0.016834167,
    "library": [
      "fn_0: (lam (logo_forLoop ?#0 (lam (lam (?#1 $0 $1 $0))) $0))"
    ],
    "egraph_min_term_size": null
  },
  {
    "method": "OursBf(num_steps=500, max_arity=2)",
    "domain": "logo",
    "file": "logo_batch_50_1h_ellisk_2019-03-23T14.02.03__bench001_it1",
    "initial_cost": 766,
    "final_cost": 725,
    "compression_ratio": 1.056551724137931,
    "elapsed_secs": 0.013603818,
    "library": [
      "fn_0: (lam (?#0 $0))"
    ],
    "egraph_min_term_size": null
  },
  {
    "method": "OursBf(num_steps=500, max_arity=2)",
    "domain": "logo",
    "file": "logo_batch_50_1h_ellisk_2019-03-23T14.02.03__bench002_it8",
    "initial_cost": 870,
    "final_cost": 815,
    "compression_ratio": 1.0674846625766872,
    "elapsed_secs": 0.015322241,
    "library": [
      "fn_0: (lam (logo_forLoop ?#0 ?#1 $0))"
    ],
    "egraph_min_term_size": null
  },
  {
    "method": "OursBf(num_steps=500, max_arity=2)",
    "domain": "logo",
    "file": "logo_batch_50_1h_ellisk_2019-03-23T14.02.03__bench003_it13",
    "initial_cost": 845,
    "final_cost": 796,
    "compression_ratio": 1.0615577889447236,
    "elapsed_secs": 0.014165941,
    "library": [
      "fn_0: (lam (?#0 $0))"
    ],
    "egraph_min_term_size": null
  },
  {
    "method": "OursBf(num_steps=500, max_arity=2)",
    "domain": "logo",
    "file": "logo_batch_50_1h_ellisk_2019-03-23T14.05.43__bench000_it0",
    "initial_cost": 841,
    "final_cost": 759,
    "compression_ratio": 1.1080368906455862,
    "elapsed_secs": 0.01356822,
    "library": [
      "fn_0: (lam (logo_FWRT ?#0 ?#1 $0))"
    ],
    "egraph_min_term_size": null
  },
  {
    "method": "OursBf(num_steps=500, max_arity=2)",
    "domain": "logo",
    "file": "logo_batch_50_1h_ellisk_2019-03-23T14.05.43__bench001_it1",
    "initial_cost": 944,
    "final_cost": 883,
    "compression_ratio": 1.0690826727066818,
    "elapsed_secs": 0.014136286,
    "library": [
      "fn_0: (lam (fn_101 (lam (?#0 ($0 ?#1))) $0))"
    ],
    "egraph_min_term_size": null
  },
  {
    "method": "OursBf(num_steps=500, max_arity=2)",
    "domain": "logo",
    "file": "logo_batch_50_1h_ellisk_2019-03-23T14.09.23__bench000_it1",
    "initial_cost": 1145,
    "final_cost": 1021,
    "compression_ratio": 1.1214495592556317,
    "elapsed_secs": 0.022299579,
    "library": [
      "fn_0: (lam (logo_forLoop ?#0 (lam (lam (?#1 $0 $1 $0))) $0))"
    ],
    "egraph_min_term_size": null
  },
  {
    "method": "OursBf(num_steps=500, max_arity=2)",
    "domain": "logo",
    "file": "logo_batch_50_1h_ellisk_2019-03-23T14.09.23__bench001_it3",
    "initial_cost": 1092,
    "final_cost": 1025,
    "compression_ratio": 1.0653658536585366,
    "elapsed_secs": 0.014713138,
    "library": [
      "fn_0: (lam (?#0 $0))"
    ],
    "egraph_min_term_size": null
  },
  {
    "method": "OursBf(num_steps=500, max_arity=2)",
    "domain": "logo",
    "file": "logo_batch_50_1h_ellisk_2019-03-23T14.13.04__bench000_it0",
    "initial_cost": 602,
    "final_cost": 538,
    "compression_ratio": 1.1189591078066914,
    "elapsed_secs": 0.014535515,
    "library": [
      "fn_0: (lam (logo_FWRT ?#0 ?#1 $0))"
    ],
    "egraph_min_term_size": null
  },
  {
    "method": "OursBf(num_steps=500, max_arity=2)",
    "domain": "logo",
    "file": "logo_batch_50_1h_ellisk_2019-03-23T14.13.04__bench001_it8",
    "initial_cost": 1596,
    "final_cost": 1516,
    "compression_ratio": 1.0527704485488127,
    "elapsed_secs": 0.021096281,
    "library": [
      "fn_0: (lam (logo_forLoop 7 (lam (lam (logo_FWRT logo_ZL (fn_115 ?#0) (logo_GETSET ?#1 $0)))) $0))"
    ],
    "egraph_min_term_size": null
  },
  {
    "method": "OursBf(num_steps=500, max_arity=2)",
    "domain": "logo",
    "file": "logo_batch_50_1h_ellisk_2019-03-23T14.16.56__bench000_it0",
    "initial_cost": 844,
    "final_cost": 747,
    "compression_ratio": 1.1298527443105757,
    "elapsed_secs": 0.014283873,
    "library": [
      "fn_0: (lam (logo_FWRT ?#0 ?#1 $0))"
    ],
    "egraph_min_term_size": null
  },
  {
    "method": "OursBf(num_steps=500, max_arity=2)",
    "domain": "logo",
    "file": "logo_batch_50_1h_ellisk_2019-03-23T14.16.56__bench001_it2",
    "initial_cost": 934,
    "final_cost": 881,
    "compression_ratio": 1.0601589103291713,
    "elapsed_secs": 0.009655441,
    "library": [
      "fn_0: (lam (?#0 $0))"
    ],
    "egraph_min_term_size": null
  }
]