[
  {
    "method": "Stitch(max_arity=2)",
    "domain": "text",
    "file": "text_ellisk_2019-01-24T21.49.39__bench000_it0",
    "initial_cost": 131,
    "final_cost": 126,
    "compression_ratio": 1.0396825396825398,
    "elapsed_secs": 0.0023338794708251953,
    "library": [
      "fn_0: (lam (lam (cons $1 $0)))"
    ],
    "egraph_min_term_size": null
  },
  {
    "method": "Stitch(max_arity=2)",
    "domain": "text",
    "file": "text_ellisk_2019-01-24T21.49.39__bench001_it1",
    "initial_cost": 194,
    "final_cost": 173,
    "compression_ratio": 1.1213872832369942,
    "elapsed_secs": 0.0024580955505371094,
    "library": [
      "fn_0: (lam (lam (cons (car $1) (cons '.' (cons (car $0) (cons '.' empty))))))"
    ],
    "egraph_min_term_size": null
  },
  {
    "method": "Stitch(max_arity=2)",
    "domain": "text",
    "file": "text_ellisk_2019-01-24T21.49.39__bench002_it2",
    "initial_cost": 210,
    "final_cost": 192,
    "compression_ratio": 1.09375,
    "elapsed_secs": 0.0019800662994384766,
    "library": [
      "fn_0: (lam (fold $0 $0 (lam (lam (if (char-eq? #0 $1) empty (cons $1 $0))))))"
    ],
    "egraph_min_term_size": null
  },
  {
    "method": "Stitch(max_arity=2)",
    "domain": "text",
    "file": "text_ellisk_2019-01-24T21.49.39__bench003_it3",
    "initial_cost": 296,
    "final_cost": 279,
    "compression_ratio": 1.060931899641577,
    "elapsed_secs": 0.0024073123931884766,
    "library": [
      "fn_0: (lam (lam (fn_170 $0 $1)))"
    ],
    "egraph_min_term_size": null
  },
  {
    "method": "Stitch(max_arity=2)",
    "domain": "text",
    "file": "text_ellisk_2019-01-24T21.49.39__bench004_it4",
    "initial_cost": 370,
    "final_cost": 353,
    "compression_ratio": 1.048158640226629,
    "elapsed_secs": 0.0027589797973632812,
    "library": [
      "fn_0: (lam (lam (fn_170 $0 $1)))"
    ],
    "egraph_min_term_size": null
  },
  {
    "method": "Stitch(max_arity=2)",
    "domain": "text",
    "file": "text_ellisk_2019-01-24T21.49.39__bench005_it5",
    "initial_cost": 389,
    "final_cost": 372,
    "compression_ratio": 1.0456989247311828,
    "elapsed_secs": 0.0024950504302978516,
    "library": [
      "fn_0: (lam (lam (fn_170 $0 $1)))"
    ],
    "egraph_min_term_size": null
  },
  {
    "method": "Stitch(max_arity=2)",
    "domain": "text",
    "file": "text_ellisk_2019-01-24T21.49.39__bench006_it6",
    "initial_cost": 445,
    "final_cost": 422,
    "compression_ratio": 1.0545023696682465,
    "elapsed_secs": 0.0027229785919189453,
    "library": [
      "fn_0: (lam (lam (fn_170 $0 $1)))"
    ],
    "egraph_min_term_size": null
  },
  {
    "method": "Stitch(max_arity=2)",
    "domain": "text",
    "file": "text_ellisk_2019-01-24T21.49.39__bench007_it7",
    "initial_cost": 480,
    "final_cost": 457,
    "compression_ratio": 1.0503282275711159,
    "elapsed_secs": 0.002907991409301758,
    "library": [
      "fn_0: (lam (lam (fn_172 $1 $0)))"
    ],
    "egraph_min_term_size": null
  },
  {
    "method": "Stitch(max_arity=2)",
    "domain": "text",
    "file": "text_ellisk_2019-01-24T21.49.39__bench008_it9",
    "initial_cost": 604,
    "final_cost": 579,
    "compression_ratio": 1.0431778929188256,
    "elapsed_secs": 0.0035326480865478516,
    "library": [
      "fn_0: (lam (lam (fn_182 $0 #1 #0 $1)))"
    ],
    "egraph_min_term_size": null
  },
  {
    "method": "Stitch(max_arity=2)",
    "domain": "text",
    "file": "text_ellisk_2019-01-24T21.49.39__bench009_it10",
    "initial_cost": 651,
    "final_cost": 622,
    "compression_ratio": 1.0466237942122187,
    "elapsed_secs": 0.003581523895263672,
    "library": [
      "fn_0: (lam (lam (fn_170 $0 $1)))"
    ],
    "egraph_min_term_size": null
  },
  {
    "method": "Stitch(max_arity=2)",
    "domain": "text",
    "file": "text_ellisk_2019-01-24T21.49.39__bench010_it15",
    "initial_cost": 742,
    "final_cost": 709,
    "compression_ratio": 1.0465444287729195,
    "elapsed_secs": 0.0041310787200927734,
    "library": [
      "fn_0: (lam (#0 $0))"
    ],
    "egraph_min_term_size": null
  },
  {
    "method": "Stitch(max_arity=2)",
    "domain": "text",
    "file": "text_ellisk_2019-01-24T21.53.45__bench000_it0",
    "initial_cost": 94,
    "final_cost": 87,
    "compression_ratio": 1.0804597701149425,
    "elapsed_secs": 0.0025472640991210938,
    "library": [
      "fn_0: (lam (map (lam (if (char-eq? $0 #1) #0 $0)) $0))"
    ],
    "egraph_min_term_size": null
  },
  {
    "method": "Stitch(max_arity=2)",
    "domain": "text",
    "file": "text_ellisk_2019-01-24T21.53.45__bench001_it4",
    "initial_cost": 303,
    "final_cost": 282,
    "compression_ratio": 1.074468085106383,
    "elapsed_secs": 0.0024733543395996094,
    "library": [
      "fn_0: (lam (lam (fn_36 $1 (#0 $0))))"
    ],
    "egraph_min_term_size": null
  },
  {
    "method": "Stitch(max_arity=2)",
    "domain": "text",
    "file": "text_ellisk_2019-01-24T21.53.45__bench002_it5",
    "initial_cost": 328,
    "final_cost": 307,
    "compression_ratio": 1.0684039087947883,
    "elapsed_secs": 0.00243377685546875,
    "library": [
      "fn_0: (lam (lam (fn_36 $1 (#0 $0))))"
    ],
    "egraph_min_term_size": null
  },
  {
    "method": "Stitch(max_arity=2)",
    "domain": "text",
    "file": "text_ellisk_2019-01-24T21.53.45__bench003_it6",
    "initial_cost": 363,
    "final_cost": 342,
    "compression_ratio": 1.0614035087719298,
    "elapsed_secs": 0.0026314258575439453,
    "library": [
      "fn_0: (lam (lam (fn_36 $1 (#0 $0))))"
    ],
    "egraph_min_term_size": null
  },
  {
    "method": "Stitch(max_arity=2)",
    "domain": "text",
    "file": "text_ellisk_2019-01-24T21.53.45__bench004_it7",
    "initial_cost": 370,
    "final_cost": 347,
    "compression_ratio": 1.0662824207492796,
    "elapsed_secs": 0.002407073974609375,
    "library": [
      "fn_0: (lam (lam (fn_189 $0 $1)))"
    ],
    "egraph_min_term_size": null
  },
  {
    "method": "Stitch(max_arity=2)",
    "domain": "text",
    "file": "text_ellisk_2019-01-24T21.53.45__bench005_it8",
    "initial_cost": 397,
    "final_cost": 374,
    "compression_ratio": 1.0614973262032086,
    "elapsed_secs": 0.002505064010620117,
    "library": [
      "fn_0: (lam (lam (fn_189 $0 $1)))"
    ],
    "egraph_min_term_size": null
  },
  {
    "method": "Stitch(max_arity=2)",
    "domain": "text",
    "file": "text_ellisk_2019-01-24T21.53.45__bench006_it10",
    "initial_cost": 476,
    "final_cost": 449,
    "compression_ratio": 1.0601336302895323,
    "elapsed_secs": 0.002879619598388672,
    "library": [
      "fn_0: (lam (lam (fn_191 $0 $1 #0)))"
    ],
    "egraph_min_term_size": null
  },
  {
    "method": "Stitch(max_arity=2)",
    "domain": "text",
    "file": "text_ellisk_2019-01-24T21.53.45__bench007_it12",
    "initial_cost": 523,
    "final_cost": 494,
    "compression_ratio": 1.0587044534412955,
    "elapsed_secs": 0.002964496612548828,
    "library": [
      "fn_0: (lam (lam (fn_189 $0 $1)))"
    ],
    "egraph_min_term_size": null
  },
  {
    "method": "Stitch(max_arity=2)",
    "domain": "text",
    "file": "text_ellisk_2019-01-24T21.53.45__bench008_it18",
    "initial_cost": 631,
    "final_cost": 602,
    "compression_ratio": 1.048172757475083,
    "elapsed_secs": 0.004012584686279297,
    "library": [
      "fn_0: (lam (#0 $0))"
    ],
    "egraph_min_term_size": null
  },
  {
    "method": "Stitch(max_arity=2)",
    "domain": "text",
    "file": "text_ellisk_2019-01-24T21.58.02__bench000_it0",
    "initial_cost": 99,
    "final_cost": 94,
    "compression_ratio": 1.053191489361702,
    "elapsed_secs": 0.0019724369049072266,
    "library": [
      "fn_0: (lam (lam (cons $1 $0)))"
    ],
    "egraph_min_term_size": null
  },
  {
    "method": "Stitch(max_arity=2)",
    "domain": "text",
    "file": "text_ellisk_2019-01-24T21.58.02__bench001_it1",
    "initial_cost": 137,
    "final_cost": 130,
    "compression_ratio": 1.0538461538461539,
    "elapsed_secs": 0.0023200511932373047,
    "library": [
      "fn_0: (cons (car #1) (cons #0 empty))"
    ],
    "egraph_min_term_size": null
  },
  {
    "method": "Stitch(max_arity=2)",
    "domain": "text",
    "file": "text_ellisk_2019-01-24T21.58.02__bench002_it2",
    "initial_cost": 185,
    "final_cost": 169,
    "compression_ratio": 1.0946745562130178,
    "elapsed_secs": 0.0020341873168945312,
    "library": [
      "fn_0: (lam (fold $0 $0 (lam (lam (cdr (if (char-eq? #0 $1) $2 $0))))))"
    ],
    "egraph_min_term_size": null
  },
  {
    "method": "Stitch(max_arity=2)",
    "domain": "text",
    "file": "text_ellisk_2019-01-24T21.58.02__bench003_it4",
    "initial_cost": 326,
    "final_cost": 309,
    "compression_ratio": 1.0550161812297734,
    "elapsed_secs": 0.002315998077392578,
    "library": [
      "fn_0: (lam (lam (fn_36 $1 $0)))"
    ],
    "egraph_min_term_size": null
  },
  {
    "method": "Stitch(max_arity=2)",
    "domain": "text",
    "file": "text_ellisk_2019-01-24T21.58.02__bench004_it5",
    "initial_cost": 394,
    "final_cost": 375,
    "compression_ratio": 1.0506666666666666,
    "elapsed_secs": 0.0027627944946289062,
    "library": [
      "fn_0: (lam (lam (fn_191 (cons #1 $0) $1 #0)))"
    ],
    "egraph_min_term_size": null
  },
  {
    "method": "Stitch(max_arity=2)",
    "domain": "text",
    "file": "text_ellisk_2019-01-24T21.58.02__bench005_it6",
    "initial_cost": 438,
    "final_cost": 411,
    "compression_ratio": 1.0656934306569343,
    "elapsed_secs": 0.0027430057525634766,
    "library": [
      "fn_0: (lam (lam (#1 $0 $1 #0)))"
    ],
    "egraph_min_term_size": null
  },
  {
    "method": "Stitch(max_arity=2)",
    "domain": "text",
    "file": "text_ellisk_2019-01-24T21.58.02__bench006_it7",
    "initial_cost": 519,
    "final_cost": 492,
    "compression_ratio": 1.0548780487804879,
    "elapsed_secs": 0.0032727718353271484,
    "library": [
      "fn_0: (lam (lam (#1 $0 $1 #0)))"
    ],
    "egraph_min_term_size": null
  },
  {
    "method": "Stitch(max_arity=2)",
    "domain": "text",
    "file": "text_ellisk_2019-01-24T21.58.02__bench007_it8",
    "initial_cost": 546,
    "final_cost": 511,
    "compression_ratio": 1.0684931506849316,
    "elapsed_secs": 0.003087759017944336,
    "library": [
      "fn_0: (lam (lam (#1 $0 $1 #0)))"
    ],
    "egraph_min_term_size": null
  },
  {
    "method": "Stitch(max_arity=2)",
    "domain": "text",
    "file": "text_ellisk_2019-01-24T21.58.02__bench008_it9",
    "initial_cost": 587,
    "final_cost": 552,
    "compression_ratio": 1.0634057971014492,
    "elapsed_secs": 0.003187894821166992,
    "library": [
      "fn_0: (lam (lam (#1 $0 $1 #0)))"
    ],
    "egraph_min_term_size": null
  },
  {
    "method": "Stitch(max_arity=2)",
    "domain": "text",
    "file": "text_ellisk_2019-01-24T21.58.02__bench009_it10",
    "initial_cost": 627,
    "final_cost": 592,
    "compression_ratio": 1.0591216216216217,
    "elapsed_secs": 0.0034155845642089844,
    "library": [
      "fn_0: (lam (lam (#1 $0 $1 #0)))"
    ],
    "egraph_min_term_size": null
  },
  {
    "method": "Stitch(max_arity=2)",
    "domain": "text",
    "file": "text_ellisk_2019-01-24T21.58.02__bench010_it12",
    "initial_cost": 754,
    "final_cost": 715,
    "compression_ratio": 1.0545454545454545,
    "elapsed_secs": 0.003856182098388672,
    "library": [
      "fn_0: (lam (lam (#1 $0 $1 #0)))"
    ],
    "egraph_min_term_size": null
  },
  {
    "method": "Stitch(max_arity=2)",
    "domain": "text",
    "file": "text_ellisk_2019-01-24T21.58.02__bench011_it15",
    "initial_cost": 808,
    "final_cost": 769,
    "compression_ratio": 1.0507152145643692,
    "elapsed_secs": 0.004624128341674805,
    "library": [
      "fn_0: (lam (lam (#1 $0 $1 #0)))"
    ],
    "egraph_min_term_size": null
  },
  {
    "method": "Stitch(max_arity=2)",
    "domain": "text",
    "file": "text_ellisk_2019-01-24T21.58.02__bench012_it16",
    "initial_cost": 814,
    "final_cost": 775,
    "compression_ratio": 1.0503225806451613,
    "elapsed_secs": 0.004500389099121094,
    "library": [
      "fn_0: (lam (lam (#1 $0 $1 #0)))"
    ],
    "egraph_min_term_size": null
  },
  {
    "method": "Stitch(max_arity=2)",
    "domain": "text",
    "file": "text_ellisk_2019-01-24T21.58.02__bench013_it19",
    "initial_cost": 805,
    "final_cost": 766,
    "compression_ratio": 1.0509138381201044,
    "elapsed_secs": 0.0039098262786865234,
    "library": [
      "fn_0: (lam (lam (#1 $0 $1 #0)))"
    ],
    "egraph_min_term_size": null
  },
  {
    "method": "Stitch(max_arity=2)",
    "domain": "text",
    "file": "text_ellisk_2019-01-24T22.01.57__bench000_it1",
    "initial_cost": 187,
    "final_cost": 168,
    "compression_ratio": 1.1130952380952381,
    "elapsed_secs": 0.0022737979888916016,
    "library": [
      "fn_0: (lam (fold #0 $0 (lam (lam (cons $1 $0)))))"
    ],
    "egraph_min_term_size": null
  },
  {
    "method": "Stitch(max_arity=2)",
    "domain": "text",
    "file": "text_ellisk_2019-01-24T22.01.57__bench001_it2",
    "initial_cost": 260,
    "final_cost": 237,
    "compression_ratio": 1.0970464135021096,
    "elapsed_secs": 0.002209186553955078,
    "library": [
      "fn_0: (lam (unfold $0 #0 (lam (car $0)) (lam (cdr $0))))"
    ],
    "egraph_min_term_size": null
  },
  {
    "method": "Stitch(max_arity=2)",
    "domain": "text",
    "file": "text_ellisk_2019-01-24T22.01.57__bench002_it3",
    "initial_cost": 338,
    "final_cost": 313,
    "compression_ratio": 1.0798722044728435,
    "elapsed_secs": 0.00359344482421875,
    "library": [
      "fn_0: (lam (fn_170 (cons RPAREN empty) (cons LPAREN $0)))"
    ],
    "egraph_min_term_size": null
  },
  {
    "method": "Stitch(max_arity=2)",
    "domain": "text",
    "file": "text_ellisk_2019-01-24T22.01.57__bench003_it4",
    "initial_cost": 346,
    "final_cost": 325,
    "compression_ratio": 1.0646153846153845,
    "elapsed_secs": 0.0027620792388916016,
    "library": [
      "fn_0: (lam (lam (#0 $0 $1)))"
    ],
    "egraph_min_term_size": null
  },
  {
    "method": "Stitch(max_arity=2)",
    "domain": "text",
    "file": "text_ellisk_2019-01-24T22.01.57__bench004_it5",
    "initial_cost": 403,
    "final_cost": 378,
    "compression_ratio": 1.066137566137566,
    "elapsed_secs": 0.0029468536376953125,
    "library": [
      "fn_0: (lam (lam (fn_170 (cons #1 (cons #0 $0)) $1)))"
    ],
    "egraph_min_term_size": null
  },
  {
    "method": "Stitch(max_arity=2)",
    "domain": "text",
    "file": "text_ellisk_2019-01-24T22.01.57__bench005_it7",
    "initial_cost": 573,
    "final_cost": 548,
    "compression_ratio": 1.0456204379562044,
    "elapsed_secs": 0.0040547847747802734,
    "library": [
      "fn_0: (lam (lam (#0 $0 $1)))"
    ],
    "egraph_min_term_size": null
  },
  {
    "method": "Stitch(max_arity=2)",
    "domain": "text",
    "file": "text_ellisk_2019-01-24T22.01.57__bench006_it8",
    "initial_cost": 646,
    "final_cost": 613,
    "compression_ratio": 1.0538336052202284,
    "elapsed_secs": 0.0037026405334472656,
    "library": [
      "fn_0: (lam (lam (#0 $0 $1)))"
    ],
    "egraph_min_term_size": null
  },
  {
    "method": "Stitch(max_arity=2)",
    "domain": "text",
    "file": "text_ellisk_2019-01-24T22.01.57__bench007_it9",
    "initial_cost": 689,
    "final_cost": 652,
    "compression_ratio": 1.0567484662576687,
    "elapsed_secs": 0.003900766372680664,
    "library": [
      "fn_0: (lam (lam (#0 $0 $1)))"
    ],
    "egraph_min_term_size": null
  },
  {
    "method": "Stitch(max_arity=2)",
    "domain": "text",
    "file": "text_ellisk_2019-01-24T22.01.57__bench008_it10",
    "initial_cost": 751,
    "final_cost": 710,
    "compression_ratio": 1.0577464788732394,
    "elapsed_secs": 0.004010677337646484,
    "library": [
      "fn_0: (lam (lam (#0 $0 $1)))"
    ],
    "egraph_min_term_size": null
  },
  {
    "method": "Stitch(max_arity=2)",
    "domain": "text",
    "file": "text_ellisk_2019-01-24T22.01.57__bench009_it11",
    "initial_cost": 806,
    "final_cost": 765,
    "compression_ratio": 1.05359477124183,
    "elapsed_secs": 0.004297971725463867,
    "library": [
      "fn_0: (lam (lam (#0 $0 $1)))"
    ],
    "egraph_min_term_size": null
  },
  {
    "method": "Stitch(max_arity=2)",
    "domain": "text",
    "file": "text_ellisk_2019-01-24T22.01.57__bench010_it12",
    "initial_cost": 863,
    "final_cost": 822,
    "compression_ratio": 1.0498783454987834,
    "elapsed_secs": 0.004319429397583008,
    "library": [
      "fn_0: (lam (lam (#0 $0 $1)))"
    ],
    "egraph_min_term_size": null
  },
  {
    "method": "Stitch(max_arity=2)",
    "domain": "text",
    "file": "text_ellisk_2019-01-24T22.05.53__bench000_it0",
    "initial_cost": 65,
    "final_cost": 54,
    "compression_ratio": 1.2037037037037037,
    "elapsed_secs": 0.0016200542449951172,
    "library": [
      "fn_0: (fold #1 #0 (lam (lam (cons $1 $0))))"
    ],
    "egraph_min_term_size": null
  },
  {
    "method": "Stitch(max_arity=2)",
    "domain": "text",
    "file": "text_ellisk_2019-01-24T22.05.53__bench001_it1",
    "initial_cost": 76,
    "final_cost": 67,
    "compression_ratio": 1.1343283582089552,
    "elapsed_secs": 0.0015883445739746094,
    "library": [
      "fn_0: (lam (fn_170 STRING $0))"
    ],
    "egraph_min_term_size": null
  },
  {
    "method": "Stitch(max_arity=2)",
    "domain": "text",
    "file": "text_ellisk_2019-01-24T22.05.53__bench002_it2",
    "initial_cost": 178,
    "final_cost": 171,
    "compression_ratio": 1.04093567251462,
    "elapsed_secs": 0.0020780563354492188,
    "library": [
      "fn_0: (lam (map (lam (if (char-eq? $0 #1) #0 $0)) $0))"
    ],
    "egraph_min_term_size": null
  },
  {
    "method": "Stitch(max_arity=2)",
    "domain": "text",
    "file": "text_ellisk_2019-01-24T22.05.53__bench003_it3",
    "initial_cost": 247,
    "final_cost": 232,
    "compression_ratio": 1.0646551724137931,
    "elapsed_secs": 0.0027315616607666016,
    "library": [
      "fn_0: (unfold #1 #0 (lam (car $0)) (lam (cdr $0)))"
    ],
    "egraph_min_term_size": null
  },
  {
    "method": "Stitch(max_arity=2)",
    "domain": "text",
    "file": "text_ellisk_2019-01-24T22.05.53__bench004_it4",
    "initial_cost": 226,
    "final_cost": 207,
    "compression_ratio": 1.0917874396135265,
    "elapsed_secs": 0.0020248889923095703,
    "library": [
      "fn_0: (lam (lam (fn_221 #1 (cons #0 $0) $1)))"
    ],
    "egraph_min_term_size": null
  },
  {
    "method": "Stitch(max_arity=2)",
    "domain": "text",
    "file": "text_ellisk_2019-01-24T22.05.53__bench005_it6",
    "initial_cost": 325,
    "final_cost": 300,
    "compression_ratio": 1.0833333333333333,
    "elapsed_secs": 0.002108335494995117,
    "library": [
      "fn_0: (lam (lam (#0 $0 $1)))"
    ],
    "egraph_min_term_size": null
  },
  {
    "method": "Stitch(max_arity=2)",
    "domain": "text",
    "file": "text_ellisk_2019-01-24T22.05.53__bench006_it9",
    "initial_cost": 581,
    "final_cost": 520,
    "compression_ratio": 1.1173076923076923,
    "elapsed_secs": 0.003095865249633789,
    "library": [
      "fn_0: (lam (lam (#0 $0 $1)))"
    ],
    "egraph_min_term_size": null
  },
  {
    "method": "Stitch(max_arity=2)",
    "domain": "text",
    "file": "text_ellisk_2019-01-24T22.05.53__bench007_it10",
    "initial_cost": 589,
    "final_cost": 528,
    "compression_ratio": 1.115530303030303,
    "elapsed_secs": 0.0031473636627197266,
    "library": [
      "fn_0: (lam (lam (#0 $0 $1)))"
    ],
    "egraph_min_term_size": null
  },
  {
    "method": "Stitch(max_arity=2)",
    "domain": "text",
    "file": "text_ellisk_2019-01-24T22.05.53__bench008_it13",
    "initial_cost": 699,
    "final_cost": 634,
    "compression_ratio": 1.1025236593059937,
    "elapsed_secs": 0.0035474300384521484,
    "library": [
      "fn_0: (lam (lam (#0 $0 $1)))"
    ],
    "egraph_min_term_size": null
  },
  {
    "method": "Stitch(max_arity=2)",
    "domain": "text",
    "file": "text_ellisk_2019-01-24T22.05.53__bench009_it15",
    "initial_cost": 711,
    "final_cost": 646,
    "compression_ratio": 1.1006191950464397,
    "elapsed_secs": 0.0036590099334716797,
    "library": [
      "fn_0: (lam (lam (#0 $0 $1)))"
    ],
    "egraph_min_term_size": null
  },
  {
    "method": "Stitch(max_arity=2)",
    "domain": "text",
    "file": "text_ellisk_2019-01-24T22.05.53__bench010_it17",
    "initial_cost": 753,
    "final_cost": 688,
    "compression_ratio": 1.0944767441860466,
    "elapsed_secs": 0.003896474838256836,
    "library": [
      "fn_0: (lam (lam (#0 $0 $1)))"
    ],
    "egraph_min_term_size": null
  },
  {
    "method": "Stitch(max_arity=2)",
    "domain": "text",
    "file": "text_ellisk_2019-01-25T20.19.06__bench000_it0",
    "initial_cost": 157,
    "final_cost": 152,
    "compression_ratio": 1.0328947368421053,
    "elapsed_secs": 0.0023550987243652344,
    "library": [
      "fn_0: (lam (lam (cons $1 $0)))"
    ],
    "egraph_min_term_size": null
  },
  {
    "method": "Stitch(max_arity=2)",
    "domain": "text",
    "file": "text_ellisk_2019-01-25T20.19.06__bench001_it1",
    "initial_cost": 248,
    "final_cost": 227,
    "compression_ratio": 1.092511013215859,
    "elapsed_secs": 0.002770662307739258,
    "library": [
      "fn_0: (lam (lam (cons (car $1) (cons '.' (cons (car $0) (cons '.' empty))))))"
    ],
    "egraph_min_term_size": null
  },
  {
    "method": "Stitch(max_arity=2)",
    "domain": "text",
    "file": "text_ellisk_2019-01-25T20.19.06__bench002_it2",
    "initial_cost": 366,
    "final_cost": 331,
    "compression_ratio": 1.105740181268882,
    "elapsed_secs": 0.0028045177459716797,
    "library": [
      "fn_0: (lam (fold $0 $0 (lam (lam (cdr (if (char-eq? $1 #0) $2 $0))))))"
    ],
    "egraph_min_term_size": null
  },
  {
    "method": "Stitch(max_arity=2)",
    "domain": "text",
    "file": "text_ellisk_2019-01-25T20.19.06__bench003_it3",
    "initial_cost": 340,
    "final_cost": 323,
    "compression_ratio": 1.0526315789473684,
    "elapsed_secs": 0.002627134323120117,
    "library": [
      "fn_0: (lam (lam (fn_170 $0 $1)))"
    ],
    "egraph_min_term_size": null
  },
  {
    "method": "Stitch(max_arity=2)",
    "domain": "text",
    "file": "text_ellisk_2019-01-25T20.19.06__bench004_it4",
    "initial_cost": 407,
    "final_cost": 390,
    "compression_ratio": 1.0435897435897437,
    "elapsed_secs": 0.0027341842651367188,
    "library": [
      "fn_0: (lam (lam (fn_170 $0 $1)))"
    ],
    "egraph_min_term_size": null
  },
  {
    "method": "Stitch(max_arity=2)",
    "domain": "text",
    "file": "text_ellisk_2019-01-25T20.19.06__bench005_it5",
    "initial_cost": 436,
    "final_cost": 419,
    "compression_ratio": 1.0405727923627686,
    "elapsed_secs": 0.002946615219116211,
    "library": [
      "fn_0: (lam (lam (fn_170 $0 $1)))"
    ],
    "egraph_min_term_size": null
  },
  {
    "method": "Stitch(max_arity=2)",
    "domain": "text",
    "file": "text_ellisk_2019-01-25T20.19.06__bench006_it6",
    "initial_cost": 482,
    "final_cost": 459,
    "compression_ratio": 1.0501089324618735,
    "elapsed_secs": 0.0031054019927978516,
    "library": [
      "fn_0: (lam (lam (fn_170 $0 $1)))"
    ],
    "egraph_min_term_size": null
  },
  {
    "method": "Stitch(max_arity=2)",
    "domain": "text",
    "file": "text_ellisk_2019-01-25T20.19.06__bench007_it9",
    "initial_cost": 670,
    "final_cost": 645,
    "compression_ratio": 1.0387596899224807,
    "elapsed_secs": 0.0037534236907958984,
    "library": [
      "fn_0: (lam (#1 $0 #0))"
    ],
    "egraph_min_term_size": null
  },
  {
    "method": "Stitch(max_arity=2)",
    "domain": "text",
    "file": "text_ellisk_2019-01-25T20.19.06__bench008_it10",
    "initial_cost": 720,
    "final_cost": 691,
    "compression_ratio": 1.0419681620839363,
    "elapsed_secs": 0.0038504600524902344,
    "library": [
      "fn_0: (lam (lam (fn_170 $0 $1)))"
    ],
    "egraph_min_term_size": null
  },
  {
    "method": "Stitch(max_arity=2)",
    "domain": "text",
    "file": "text_ellisk_2019-01-25T20.19.06__bench009_it11",
    "initial_cost": 762,
    "final_cost": 733,
    "compression_ratio": 1.03956343792633,
    "elapsed_secs": 0.0039288997650146484,
    "library": [
      "fn_0: (lam (#1 $0 #0))"
    ],
    "egraph_min_term_size": null
  }
]