[
  {
    "method": "OursSmc(num_steps=100, num_particles=1000, temperature=1000.0, max_arity=2)",
    "domain": "towers",
    "file": "tower_batch_50_3600_ellisk_2019-03-26T10.51.16__bench000_it0",
    "initial_cost": 406,
    "final_cost": 194,
    "compression_ratio": 2.0927835051546393,
    "elapsed_secs": 0.436615586,
    "library": [
      "fn_0: (lam (moveHand 3 (reverseHand (tower_loopM ?#0 (lam (lam (moveHand 6 (3x1 $0)))) $0))))",
      "fn_1: (lam (tower_loopM ?#0 (lam (fn_0 ?#1)) $0))",
      "fn_2: (lam (tower_loopM ?#0 (lam (lam (1x3 (moveHand 4 (1x3 (reverseHand $0)))))) (moveHand 2 (3x1 $0))))",
      "fn_3: (lam (tower_loopM ?#0 (lam (lam (reverseHand (tower_embed (lam (moveHand 2 (1x3 $0))) $0)))) (3x1 $0)))",
      "fn_4: (fn_1 6)",
      "fn_5: (moveHand 6)",
      "fn_6: (fn_1 2)",
      "fn_7: (fn_1 4)"
    ],
    "egraph_min_term_size": null
  },
  {
    "method": "OursSmc(num_steps=100, num_particles=1000, temperature=1000.0, max_arity=2)",
    "domain": "towers",
    "file": "tower_batch_50_3600_ellisk_2019-03-26T10.51.16__bench001_it1",
    "initial_cost": 672,
    "final_cost": 334,
    "compression_ratio": 2.0119760479041915,
    "elapsed_secs": 0.585089629,
    "library": [
      "fn_244: (lam (fn_242 (?#0 $0) (lam (reverseHand $0)) ?#1))",
      "fn_245: (lam (tower_loopM ?#0 (lam ?#1) $0))",
      "fn_246: (fn_245 ?#0 (fn_244 (moveHand 4) ?#1))",
      "fn_247: (fn_242 ?#0 (lam (reverseHand $0)))",
      "fn_248: (lam (fn_243 ?#0 ?#1 $0))",
      "fn_249: (fn_242 ?#0 (lam (1x3 (reverseHand $0))))",
      "fn_250: (lam (fn_249 (reverseHand (moveHand 4 $0)) 5))",
      "fn_251: (fn_245 4)",
      "fn_252: (fn_246 ?#0 4)",
      "fn_253: (fn_245 3)",
      "fn_254: (fn_248 5)",
      "fn_255: (moveHand 4)",
      "fn_256: (fn_248 4)",
      "fn_257: (lam (fn_247 $0 ?#0))",
      "fn_258: (fn_248 6)",
      "fn_259: (fn_245 6)",
      "fn_260: (fn_243 6)",
      "fn_261: (moveHand 6)",
      "fn_262: (moveHand 5)",
      "fn_263: (fn_246 ?#0 6)"
    ],
    "egraph_min_term_size": null
  },
  {
    "method": "OursSmc(num_steps=100, num_particles=1000, temperature=1000.0, max_arity=2)",
    "domain": "towers",
    "file": "tower_batch_50_3600_ellisk_2019-03-26T10.51.16__bench002_it3",
    "initial_cost": 571,
    "final_cost": 384,
    "compression_ratio": 1.4869791666666667,
    "elapsed_secs": 0.581517899,
    "library": [
      "fn_251: (lam (?#0 $0))",
      "fn_252: (lam (tower_embed (fn_251 (?#0 ?#1)) (fn_246 2 ?#1 $0)))",
      "fn_253: (lam (fn_251 (tower_embed (lam (fn_246 2 $1 $0)))))",
      "fn_254: (fn_251 (fn_246 ?#0 ?#1))",
      "fn_255: (fn_251 (tower_loopM 4 ?#0))",
      "fn_256: (fn_251 (fn_243 ?#0 ?#1))",
      "fn_257: (moveHand 6)",
      "fn_258: (fn_254 4)",
      "fn_259: (fn_254 6)",
      "fn_260: (fn_254 2)",
      "fn_261: (lam (?#0 (?#1 $0)))",
      "fn_262: (fn_256 5)",
      "fn_263: (fn_256 4)",
      "fn_264: (fn_251 (fn_244 ?#0))",
      "fn_265: (lam (?#0 (reverseHand (fn_257 (fn_250 (?#1 (fn_245 $0)))))))",
      "fn_266: (tower_loopM 7 fn_253)",
      "fn_267: (fn_256 6)",
      "fn_268: (fn_252 fn_247)",
      "fn_269: (fn_243 6)",
      "fn_270: (fn_261 fn_257)"
    ],
    "egraph_min_term_size": null
  },
  {
    "method": "OursSmc(num_steps=100, num_particles=1000, temperature=1000.0, max_arity=2)",
    "domain": "towers",
    "file": "tower_batch_50_3600_ellisk_2019-03-26T10.51.16__bench003_it9",
    "initial_cost": 569,
    "final_cost": 403,
    "compression_ratio": 1.411910669975186,
    "elapsed_secs": 1.053477412,
    "library": [
      "fn_254: (lam (?#0 $0))",
      "fn_255: (lam (moveHand 6 (tower_embed (lam (reverseHand (fn_249 1 2 ?#0 $0))) $0)))",
      "fn_256: (fn_254 (?#0 4))",
      "fn_257: (fn_254 (?#0 4 ?#1))",
      "fn_258: (lam (?#0 ?#1 (fn_251 ?#1 $0)))",
      "fn_259: (fn_246 6)",
      "fn_260: (fn_243 6)",
      "fn_261: (fn_243 5)",
      "fn_262: (fn_257 fn_246)",
      "fn_263: (fn_254 (?#0 3))",
      "fn_264: (lam (fn_255 $0))",
      "fn_265: (moveHand 6)",
      "fn_266: (fn_251 5)",
      "fn_267: (fn_257 fn_243)",
      "fn_268: (fn_254 (?#0 6))",
      "fn_269: (fn_254 (?#0 2))",
      "fn_270: (fn_254 (?#0 7))",
      "fn_271: (lam (lam (moveHand 3 (?#0 $0))))",
      "fn_272: (lam (reverseHand (fn_252 ?#0 $0)))",
      "fn_273: (fn_257 tower_loopM)"
    ],
    "egraph_min_term_size": null
  },
  {
    "method": "OursSmc(num_steps=100, num_particles=1000, temperature=1000.0, max_arity=2)",
    "domain": "towers",
    "file": "tower_batch_50_3600_ellisk_2019-03-26T10.54.52__bench000_it0",
    "initial_cost": 376,
    "final_cost": 190,
    "compression_ratio": 1.9789473684210526,
    "elapsed_secs": 0.424666032,
    "library": [
      "fn_0: (?#0 (lam (lam (moveHand 3 (reverseHand (tower_loopM ?#1 (lam (lam (moveHand 6 (3x1 $0)))) $0))))))",
      "fn_1: (lam (tower_loopM ?#0 (lam (lam (1x3 (moveHand 4 (1x3 (reverseHand $0)))))) (moveHand 2 (3x1 $0))))",
      "fn_2: (lam (lam (reverseHand (tower_embed (lam (moveHand 2 (1x3 $0))) $0))))",
      "fn_3: (lam (fn_0 (tower_loopM ?#0) ?#1 $0))",
      "fn_4: (lam (tower_loopM ?#0 fn_2 (3x1 $0)))",
      "fn_5: (fn_3 6)",
      "fn_6: (lam (tower_loopM ?#0 (lam ?#1) $0))",
      "fn_7: (fn_3 2)",
      "fn_8: (moveHand 2)"
    ],
    "egraph_min_term_size": null
  },
  {
    "method": "OursSmc(num_steps=100, num_particles=1000, temperature=1000.0, max_arity=2)",
    "domain": "towers",
    "file": "tower_batch_50_3600_ellisk_2019-03-26T10.54.52__bench001_it1",
    "initial_cost": 679,
    "final_cost": 333,
    "compression_ratio": 2.039039039039039,
    "elapsed_secs": 0.550936556,
    "library": [
      "fn_244: (lam (lam (fn_242 (moveHand 4 $0) (lam (reverseHand $0)) ?#0)))",
      "fn_245: (lam (tower_loopM ?#0 ?#1 $0))",
      "fn_246: (fn_242 ?#0 (lam (reverseHand $0)))",
      "fn_247: (fn_245 ?#0 (fn_244 ?#1))",
      "fn_248: (lam (fn_243 ?#0 ?#1 $0))",
      "fn_249: (fn_242 ?#0 (lam (1x3 (reverseHand $0))))",
      "fn_250: (fn_245 4 (lam ?#0))",
      "fn_251: (moveHand 4)",
      "fn_252: (fn_246 ?#0 2)",
      "fn_253: (fn_247 ?#0 4)",
      "fn_254: (lam (?#0 (moveHand ?#1 $0)))",
      "fn_255: (fn_245 3)",
      "fn_256: (fn_248 5)",
      "fn_257: (fn_248 4)",
      "fn_258: (fn_247 ?#0 6)",
      "fn_259: (fn_247 ?#0 2)",
      "fn_260: (fn_243 6)",
      "fn_261: (fn_248 6)",
      "fn_262: (fn_254 fn_252)",
      "fn_263: (fn_249 ?#0 5)"
    ],
    "egraph_min_term_size": null
  },
  {
    "method": "OursSmc(num_steps=100, num_particles=1000, temperature=1000.0, max_arity=2)",
    "domain": "towers",
    "file": "tower_batch_50_3600_ellisk_2019-03-26T10.54.52__bench002_it2",
    "initial_cost": 579,
    "final_cost": 400,
    "compression_ratio": 1.4475,
    "elapsed_secs": 0.822200272,
    "library": [
      "fn_258: (lam (fn_255 ?#0 ?#1 $0))",
      "fn_259: (lam (?#0 $0))",
      "fn_260: (tower_loopM ?#0 (lam (fn_259 (tower_embed (fn_258 $0 2)))))",
      "fn_261: (fn_259 (fn_243 ?#0 ?#1))",
      "fn_262: (lam (tower_embed ?#0 (fn_255 ?#1 2 $0)))",
      "fn_263: (fn_259 (tower_loopM 4 (lam (lam (?#0 (?#1 $0))))))",
      "fn_264: (moveHand 6)",
      "fn_265: (lam (fn_254 $0 ?#0))",
      "fn_266: (fn_258 6)",
      "fn_267: (fn_258 4)",
      "fn_268: (fn_261 4)",
      "fn_269: (fn_258 3)",
      "fn_270: (fn_261 5)",
      "fn_271: (fn_259 (fn_256 ?#0))",
      "fn_272: (lam (reverseHand (?#0 $0)))",
      "fn_273: (lam (lam (moveHand 3 (?#0 $0))))",
      "fn_274: (lam (?#0 (reverseHand (fn_264 (fn_250 (?#1 (fn_245 $0)))))))",
      "fn_275: (fn_261 6)",
      "fn_276: (fn_243 6)",
      "fn_277: (tower_loopM 6)"
    ],
    "egraph_min_term_size": null
  },
  {
    "method": "OursSmc(num_steps=100, num_particles=1000, temperature=1000.0, max_arity=2)",
    "domain": "towers",
    "file": "tower_batch_50_3600_ellisk_2019-03-26T10.54.52__bench003_it13",
    "initial_cost": 536,
    "final_cost": 389,
    "compression_ratio": 1.3778920308483291,
    "elapsed_secs": 0.563188418,
    "library": [
      "fn_261: (lam (?#0 $0))",
      "fn_262: (lam (tower_embed (lam (reverseHand (?#0 $0))) (moveHand 6 $0)))",
      "fn_263: (fn_261 (?#0 4))",
      "fn_264: (lam (fn_258 $0 ?#0))",
      "fn_265: (fn_261 (?#0 6))",
      "fn_266: (lam (fn_262 (fn_257 $0 1 2)))",
      "fn_267: (lam (?#0 (fn_258 $0 ?#1)))",
      "fn_268: (lam (fn_254 $0 ?#0))",
      "fn_269: (fn_243 6)",
      "fn_270: (fn_243 5)",
      "fn_271: (fn_263 (fn_255 ?#0))",
      "fn_272: (fn_261 (?#0 2))",
      "fn_273: (fn_261 (tower_loopM ?#0 ?#1))",
      "fn_274: (fn_273 6)",
      "fn_275: (fn_243 4)",
      "fn_276: (fn_265 (fn_255 ?#0))",
      "fn_277: (lam (reverseHand (fn_259 ?#0 $0)))",
      "fn_278: (fn_273 4)",
      "fn_279: (fn_243 3)",
      "fn_280: (moveHand 3)"
    ],
    "egraph_min_term_size": null
  },
  {
    "method": "OursSmc(num_steps=100, num_particles=1000, temperature=1000.0, max_arity=2)",
    "domain": "towers",
    "file": "tower_batch_50_3600_ellisk_2019-03-26T10.58.24__bench000_it0",
    "initial_cost": 92,
    "final_cost": 74,
    "compression_ratio": 1.2432432432432432,
    "elapsed_secs": 0.125437951,
    "library": [
      "fn_0: (lam (lam (reverseHand (tower_embed (lam (moveHand 2 (1x3 $0))) $0))))",
      "fn_1: (lam (tower_loopM ?#0 fn_0 (3x1 $0)))"
    ],
    "egraph_min_term_size": null
  },
  {
    "method": "OursSmc(num_steps=100, num_particles=1000, temperature=1000.0, max_arity=2)",
    "domain": "towers",
    "file": "tower_batch_50_3600_ellisk_2019-03-26T10.58.24__bench001_it1",
    "initial_cost": 608,
    "final_cost": 341,
    "compression_ratio": 1.782991202346041,
    "elapsed_secs": 0.748412383,
    "library": [
      "fn_262: (lam (tower_loopM ?#0 ?#1 $0))",
      "fn_263: (lam (lam (fn_261 (moveHand 6 $0) ?#0)))",
      "fn_264: (moveHand 6 (tower_loopM ?#0 (lam (lam (fn_261 $0 2))) ?#1))",
      "fn_265: (fn_261 ?#0 2)",
      "fn_266: (lam (lam (fn_264 $1 $0)))",
      "fn_267: (lam (lam (moveHand 3 (reverseHand (tower_loopM ?#0 (lam (lam (moveHand 6 (3x1 $0)))) $0)))))",
      "fn_268: (fn_262 ?#0 (fn_263 ?#1))",
      "fn_269: (fn_265 (moveHand 6 ?#0))",
      "fn_270: (lam (lam (?#0 (moveHand ?#1 $0))))",
      "fn_271: (fn_262 4)",
      "fn_272: (moveHand 4)",
      "fn_273: (lam (reverseHand (tower_loopM ?#0 fn_266 $0)))",
      "fn_274: (fn_268 6)",
      "fn_275: (moveHand 2)",
      "fn_276: (fn_261 ?#0 6)",
      "fn_277: (fn_261 ?#0 8)",
      "fn_278: (fn_262 6)",
      "fn_279: (fn_268 3)",
      "fn_280: (fn_268 7)",
      "fn_281: (fn_262 5)"
    ],
    "egraph_min_term_size": null
  },
  {
    "method": "OursSmc(num_steps=100, num_particles=1000, temperature=1000.0, max_arity=2)",
    "domain": "towers",
    "file": "tower_batch_50_3600_ellisk_2019-03-26T10.58.24__bench002_it3",
    "initial_cost": 541,
    "final_cost": 390,
    "compression_ratio": 1.3871794871794871,
    "elapsed_secs": 0.625359054,
    "library": [
      "fn_267: (lam (?#0 $0))",
      "fn_268: (fn_267 (tower_loopM ?#0 (lam (lam (fn_262 (reverseHand (?#1 4 $0)))))))",
      "fn_269: (fn_267 (fn_264 ?#0 ?#1))",
      "fn_270: (lam (fn_266 ?#0 (fn_264 2 4 (moveHand 6 (reverseHand (fn_266 4 $0))))))",
      "fn_271: (fn_267 (fn_243 ?#0 ?#1))",
      "fn_272: (fn_269 4)",
      "fn_273: (lam (reverseHand (fn_266 ?#0 $0)))",
      "fn_274: (lam (fn_264 ?#0 ?#1 (reverseHand (fn_265 ?#1 6 $0))))",
      "fn_275: (fn_269 6)",
      "fn_276: (fn_267 (tower_loopM ?#0 (lam ?#1)))",
      "fn_277: (fn_271 5)",
      "fn_278: (fn_271 4)",
      "fn_279: (fn_269 2)",
      "fn_280: (lam (fn_261 $0 ?#0))",
      "fn_281: (fn_271 6)",
      "fn_282: (fn_265 1)",
      "fn_283: (fn_243 6)",
      "fn_284: (moveHand 7)",
      "fn_285: (fn_276 4)",
      "fn_286: (fn_268 4)"
    ],
    "egraph_min_term_size": null
  },
  {
    "method": "OursSmc(num_steps=100, num_particles=1000, temperature=1000.0, max_arity=2)",
    "domain": "towers",
    "file": "tower_batch_50_3600_ellisk_2019-03-26T10.58.24__bench003_it5",
    "initial_cost": 511,
    "final_cost": 394,
    "compression_ratio": 1.2969543147208122,
    "elapsed_secs": 0.614818864,
    "library": [
      "fn_270: (lam (?#0 $0))",
      "fn_271: (fn_270 (tower_loopM ?#0 (lam (lam (moveHand 6 (tower_embed (lam (reverseHand (fn_265 $2 3 $0))) $0))))))",
      "fn_272: (fn_270 (?#0 4 ?#1))",
      "fn_273: (fn_272 fn_264)",
      "fn_274: (?#0 6 6)",
      "fn_275: (lam (reverseHand (fn_266 ?#0 $0)))",
      "fn_276: (fn_243 5)",
      "fn_277: (fn_270 (?#0 4))",
      "fn_278: (fn_272 fn_243)",
      "fn_279: (fn_270 (?#0 7))",
      "fn_280: (lam (fn_261 $0 ?#0))",
      "fn_281: (fn_243 6)",
      "fn_282: (fn_264 6)",
      "fn_283: (fn_274 fn_264)",
      "fn_284: (fn_265 3)",
      "fn_285: (fn_274 fn_243)",
      "fn_286: (fn_274 fn_265)",
      "fn_287: (fn_264 8)",
      "fn_288: (moveHand 7)",
      "fn_289: (fn_243 3)"
    ],
    "egraph_min_term_size": null
  },
  {
    "method": "OursSmc(num_steps=100, num_particles=1000, temperature=1000.0, max_arity=2)",
    "domain": "towers",
    "file": "tower_batch_50_3600_ellisk_2019-03-26T11.01.50__bench000_it0",
    "initial_cost": 376,
    "final_cost": 197,
    "compression_ratio": 1.9086294416243654,
    "elapsed_secs": 0.406195747,
    "library": [
      "fn_0: (tower_loopM ?#0 (lam (lam (moveHand 3 (reverseHand (tower_loopM ?#1 (lam (lam (moveHand 6 (3x1 $0)))) $0))))))",
      "fn_1: (tower_loopM ?#0 (lam (lam (1x3 (moveHand 4 (1x3 (reverseHand $0)))))) (moveHand 2 (3x1 ?#1)))",
      "fn_2: (lam (tower_loopM ?#0 (lam (lam (reverseHand (tower_embed (lam (moveHand 2 (1x3 $0))) $0)))) (3x1 $0)))",
      "fn_3: (lam (fn_0 ?#0 ?#1 $0))",
      "fn_4: (fn_3 6)",
      "fn_5: (moveHand 6)",
      "fn_6: (fn_3 4)"
    ],
    "egraph_min_term_size": null
  },
  {
    "method": "OursSmc(num_steps=100, num_particles=1000, temperature=1000.0, max_arity=2)",
    "domain": "towers",
    "file": "tower_batch_50_3600_ellisk_2019-03-26T11.01.50__bench001_it1",
    "initial_cost": 695,
    "final_cost": 366,
    "compression_ratio": 1.8989071038251366,
    "elapsed_secs": 0.913660119,
    "library": [
      "fn_271: (lam (fn_270 (moveHand ?#0 $0) ?#1 (lam (reverseHand $0))))",
      "fn_272: (lam (tower_loopM ?#0 ?#1 $0))",
      "fn_273: (fn_272 ?#0 (lam (fn_271 4 ?#1)))",
      "fn_274: (fn_270 ?#0 ?#1 (lam (reverseHand $0)))",
      "fn_275: (fn_270 ?#0 ?#1 (lam (1x3 (reverseHand $0))))",
      "fn_276: (lam (fn_243 ?#0 ?#1 $0))",
      "fn_277: (fn_272 4 (lam ?#0))",
      "fn_278: (moveHand 4)",
      "fn_279: (lam (moveHand 6 (tower_embed ?#0 $0)))",
      "fn_280: (fn_273 6)",
      "fn_281: (fn_273 3)",
      "fn_282: (fn_272 3)",
      "fn_283: (fn_276 5)",
      "fn_284: (fn_276 4)",
      "fn_285: (lam (fn_274 $0 ?#0))",
      "fn_286: (fn_243 6)",
      "fn_287: (fn_276 6)",
      "fn_288: (fn_273 5)",
      "fn_289: (fn_273 4)",
      "fn_290: (moveHand 3)"
    ],
    "egraph_min_term_size": null
  },
  {
    "method": "OursSmc(num_steps=100, num_particles=1000, temperature=1000.0, max_arity=2)",
    "domain": "towers",
    "file": "tower_batch_50_3600_ellisk_2019-03-26T11.01.50__bench002_it3",
    "initial_cost": 626,
    "final_cost": 417,
    "compression_ratio": 1.501199040767386,
    "elapsed_secs": 0.830620606,
    "library": [
      "fn_275: (lam (?#0 $0))",
      "fn_276: (tower_loopM ?#0 (lam (fn_275 (tower_embed (lam (fn_272 $1 2 $0))))))",
      "fn_277: (fn_275 (fn_272 ?#0 ?#1))",
      "fn_278: (lam (moveHand 6 (tower_embed ?#0 $0)))",
      "fn_279: (lam (fn_273 ?#0 (moveHand 2 (reverseHand (fn_272 ?#0 2 $0)))))",
      "fn_280: (fn_275 (fn_243 ?#0 ?#1))",
      "fn_281: (fn_277 ?#0 2)",
      "fn_282: (fn_275 (tower_loopM ?#0 ?#1))",
      "fn_283: (lam (fn_271 $0 ?#0))",
      "fn_284: (fn_277 ?#0 6)",
      "fn_285: (fn_277 ?#0 4)",
      "fn_286: (fn_282 ?#0 (lam (fn_278 (fn_281 ?#0))))",
      "fn_287: (fn_280 5)",
      "fn_288: (fn_280 4)",
      "fn_289: (lam (?#0 (?#1 $0)))",
      "fn_290: (fn_243 6)",
      "fn_291: (fn_280 6)",
      "fn_292: (fn_284 6)",
      "fn_293: (fn_276 7)",
      "fn_294: (fn_281 2)"
    ],
    "egraph_min_term_size": null
  },
  {
    "method": "OursSmc(num_steps=100, num_particles=1000, temperature=1000.0, max_arity=2)",
    "domain": "towers",
    "file": "tower_batch_50_3600_ellisk_2019-03-26T11.05.16__bench000_it0",
    "initial_cost": 532,
    "final_cost": 273,
    "compression_ratio": 1.9487179487179487,
    "elapsed_secs": 0.579440873,
    "library": [
      "fn_0: (lam (moveHand 3 (reverseHand (tower_loopM ?#0 (lam (lam (moveHand 6 (3x1 $0)))) $0))))",
      "fn_1: (lam (tower_loopM ?#0 (lam ?#1) $0))",
      "fn_2: (tower_embed (lam (moveHand 2 (1x3 $0))))",
      "fn_3: (moveHand 4 (1x3 ?#0))",
      "fn_4: (lam (lam (moveHand 6 (tower_embed (lam (moveHand 3 (3x1 $0))) (3x1 $0)))))",
      "fn_5: (lam (tower_loopM ?#0 (lam (lam (1x3 (fn_3 (reverseHand $0))))) (moveHand 2 (3x1 $0))))",
      "fn_6: (lam (tower_loopM ?#0 (lam (lam (reverseHand (fn_2 $0)))) (3x1 $0)))",
      "fn_7: (moveHand 2)",
      "fn_8: (fn_1 6)",
      "fn_9: (fn_3 (fn_3 (reverseHand (fn_7 (3x1 ?#0)))))",
      "fn_10: (lam (reverseHand (tower_loopM ?#0 fn_4 $0)))",
      "fn_11: (fn_1 3)",
      "fn_12: (fn_1 4)",
      "fn_13: (fn_1 5)",
      "fn_14: (fn_0 6)",
      "fn_15: (fn_0 5)",
      "fn_16: (fn_7 (fn_2 (3x1 ?#0)))"
    ],
    "egraph_min_term_size": null
  },
  {
    "method": "OursSmc(num_steps=100, num_particles=1000, temperature=1000.0, max_arity=2)",
    "domain": "towers",
    "file": "tower_batch_50_3600_ellisk_2019-03-26T11.05.16__bench001_it1",
    "initial_cost": 641,
    "final_cost": 411,
    "compression_ratio": 1.559610705596107,
    "elapsed_secs": 0.993078518,
    "library": [
      "fn_279: (lam (tower_loopM ?#0 (lam (?#1 $0)) $0))",
      "fn_280: (fn_279 ?#0 (lam (lam (fn_275 (moveHand 4 $0) 2))))",
      "fn_281: (lam (lam (fn_275 (reverseHand (moveHand 4 $0)) ?#0)))",
      "fn_282: (lam (fn_276 ?#0 4 $0))",
      "fn_283: (moveHand 4 (reverseHand (fn_276 1 2 ?#0)))",
      "fn_284: (lam (fn_243 ?#0 ?#1 $0))",
      "fn_285: (fn_279 4)",
      "fn_286: (moveHand 4)",
      "fn_287: (lam (lam (tower_embed (fn_282 $1) $0)))",
      "fn_288: (lam (fn_275 $0 ?#0))",
      "fn_289: (fn_279 6)",
      "fn_290: (lam (lam (fn_286 (fn_275 (fn_283 $0) ?#0))))",
      "fn_291: (fn_278 (lam ($0 2)))",
      "fn_292: (fn_281 3)",
      "fn_293: (fn_276 4)",
      "fn_294: (lam (reverseHand (?#0 $0)))",
      "fn_295: (fn_284 6)",
      "fn_296: (fn_279 7)",
      "fn_297: (fn_281 5)",
      "fn_298: (fn_276 3)"
    ],
    "egraph_min_term_size": null
  },
  {
    "method": "OursSmc(num_steps=100, num_particles=1000, temperature=1000.0, max_arity=2)",
    "domain": "towers",
    "file": "tower_batch_50_3600_ellisk_2019-03-26T11.05.16__bench002_it2",
    "initial_cost": 528,
    "final_cost": 367,
    "compression_ratio": 1.438692098092643,
    "elapsed_secs": 0.544641909,
    "library": [
      "fn_284: (lam (lam (moveHand 6 (tower_embed (lam (reverseHand (fn_276 $2 1 $0))) $0))))",
      "fn_285: (lam (?#0 $0))",
      "fn_286: (fn_285 (?#0 4))",
      "fn_287: (lam (fn_275 $0 ?#0))",
      "fn_288: (fn_285 (?#0 6))",
      "fn_289: (lam (fn_282 ?#0 (moveHand 6 (reverseHand (fn_282 ?#1 $0)))))",
      "fn_290: (fn_243 6)",
      "fn_291: (fn_280 3)",
      "fn_292: (fn_285 (tower_loopM ?#0 fn_284))",
      "fn_293: (fn_287 5)",
      "fn_294: (fn_243 5)",
      "fn_295: (moveHand 3)",
      "fn_296: (fn_286 (fn_276 ?#0))",
      "fn_297: (fn_285 (?#0 7))",
      "fn_298: (lam (reverseHand (fn_282 ?#0 $0)))",
      "fn_299: (fn_282 3)",
      "fn_300: (fn_287 3)",
      "fn_301: (fn_287 4)",
      "fn_302: (fn_283 fn_293)",
      "fn_303: (fn_280 5)"
    ],
    "egraph_min_term_size": null
  }
]